pelican/plugins/pandoc_reader/__init__.py
pelican/plugins/pandoc_reader/filters/wordcount.lua
pelican/plugins/pandoc_reader/pandoc_reader.py
pelican/plugins/pandoc_reader/templates/pandoc-reader-default.html
pelican/plugins/pandoc_reader/test/defaults_files/from_reader_both_given.yaml
pelican/plugins/pandoc_reader/test/defaults_files/invalid_from_input_format.yaml
pelican/plugins/pandoc_reader/test/defaults_files/invalid_reader_input_format.yaml
pelican/plugins/pandoc_reader/test/defaults_files/invalid_to_output_format.yaml
pelican/plugins/pandoc_reader/test/defaults_files/invalid_writer_output_format.yaml
pelican/plugins/pandoc_reader/test/defaults_files/no_input_format.yaml
pelican/plugins/pandoc_reader/test/defaults_files/no_output_format.yaml
pelican/plugins/pandoc_reader/test/defaults_files/self_contained_true.yaml
pelican/plugins/pandoc_reader/test/defaults_files/standalone_true.yaml
pelican/plugins/pandoc_reader/test/defaults_files/to_writer_both_given.yaml
pelican/plugins/pandoc_reader/test/defaults_files/valid_defaults.yaml
pelican/plugins/pandoc_reader/test/defaults_files/valid_defaults_file_1.yaml
pelican/plugins/pandoc_reader/test/defaults_files/valid_defaults_file_2.yaml
pelican/plugins/pandoc_reader/test/defaults_files/valid_defaults_with_citeproc_filter.yaml
pelican/plugins/pandoc_reader/test/defaults_files/valid_defaults_with_toc.yaml
pelican/plugins/pandoc_reader/test/defaults_files/valid_defaults_with_toc_and_citations.yaml
pelican/plugins/pandoc_reader/test/defaults_files/valid_first_defaults_file_dup_keys.yaml
pelican/plugins/pandoc_reader/test/defaults_files/valid_first_defaults_file_reader.yaml
pelican/plugins/pandoc_reader/test/defaults_files/valid_first_defaults_file_writer.yaml
pelican/plugins/pandoc_reader/test/defaults_files/valid_second_defaults_file_dup_keys.yaml
pelican/plugins/pandoc_reader/test/defaults_files/valid_second_defaults_file_reader.yaml
pelican_pandoc_reader-3.0.0.dist-info/METADATA
pelican_pandoc_reader-3.0.0.dist-info/WHEEL
pelican_pandoc_reader-3.0.0.dist-info/RECORD
