Metadata-Version: 2.1
Name: pelican-pandoc-reader
Version: 3.0.0
Summary: Pelican plugin for converting Pandoc's Markdown variant to HTML.
Home-page: https://github.com/pelican-plugins/pandoc-reader
License: AGPL-3.0
Keywords: pelican,plugin,markdown,pandoc
Author: Nandakumar Chandrasekhar
Author-email: navanitachora@gmail.com
Requires-Python: >=3.9.0,<4.0
Classifier: Development Status :: 5 - Production/Stable
Classifier: Environment :: Console
Classifier: Framework :: Pelican
Classifier: Framework :: Pelican :: Plugins
Classifier: Intended Audience :: End Users/Desktop
Classifier: License :: OSI Approved :: GNU Affero General Public License v3
Classifier: Operating System :: OS Independent
Classifier: Programming Language :: Python :: 3
Classifier: Programming Language :: Python :: 3.9
Classifier: Programming Language :: Python :: 3.10
Classifier: Programming Language :: Python :: 3.11
Classifier: Programming Language :: Python :: 3.12
Classifier: Programming Language :: Python :: 3.13
Classifier: Topic :: Internet :: WWW/HTTP
Classifier: Topic :: Software Development :: Libraries :: Python Modules
Provides-Extra: markdown
Requires-Dist: beautifulsoup4 (>=4.9.3,<5.0.0)
Requires-Dist: docutils (>=0.21.2,<0.22.0)
Requires-Dist: markdown (>=3.6) ; extra == "markdown"
Requires-Dist: pelican (>=4.5)
Requires-Dist: pyyaml (>=6.0.0,<7.0.0)
Requires-Dist: ruamel.yaml (>=0.17.32,<0.18.0)
Project-URL: Documentation, https://docs.getpelican.com
Project-URL: Funding, https://donate.getpelican.com/
Project-URL: Issue Tracker, https://github.com/pelican-plugins/pandoc-reader/issues
Project-URL: Repository, https://github.com/pelican-plugins/pandoc-reader
